expops/__init__.py
expops/__main__.py
expops/main.py
expops/web/__init__.py
expops/web/server.py
expops-0.1.8.dist-info/licenses/LICENSE
mlops/__init__.py
mlops/__main__.py
mlops/_version.py
mlops/main.py
mlops/platform.py
mlops/adapters/__init__.py
mlops/adapters/base.py
mlops/adapters/config_schema.py
mlops/adapters/plugin_manager.py
mlops/adapters/custom/__init__.py
mlops/adapters/custom/custom_adapter.py
mlops/adapters/sklearn/__init__.py
mlops/adapters/sklearn/adapter.py
mlops/cluster/__init__.py
mlops/cluster/controller.py
mlops/cluster/process_runner.py
mlops/cluster/providers.py
mlops/core/__init__.py
mlops/core/custom_model_base.py
mlops/core/dask_networkx_executor.py
mlops/core/executor_worker.py
mlops/core/experiment_tracker.py
mlops/core/graph_types.py
mlops/core/networkx_parser.py
mlops/core/payload_spill.py
mlops/core/pipeline_utils.py
mlops/core/process_hashing.py
mlops/core/step_state_manager.py
mlops/core/step_system.py
mlops/core/workspace.py
mlops/environment/__init__.py
mlops/environment/base.py
mlops/environment/conda_manager.py
mlops/environment/factory.py
mlops/environment/pyenv_manager.py
mlops/environment/setup_env.py
mlops/environment/system_manager.py
mlops/environment/utils.py
mlops/environment/venv_manager.py
mlops/managers/project_manager.py
mlops/managers/reproducibility_manager.py
mlops/reporting/__init__.py
mlops/reporting/context.py
mlops/reporting/entrypoint.py
mlops/reporting/kv_utils.py
mlops/reporting/registry.py
mlops/runtime/__init__.py
mlops/runtime/context.py
mlops/runtime/env_export.py
mlops/storage/__init__.py
mlops/storage/factory.py
mlops/storage/path_utils.py
mlops/storage/adapters/__init__.py
mlops/storage/adapters/gcp_kv_store.py
mlops/storage/adapters/gcs_object_store.py
mlops/storage/adapters/memory_store.py
mlops/storage/adapters/redis_store.py
mlops/storage/interfaces/__init__.py
mlops/storage/interfaces/kv_store.py
mlops/templates/premier-league/requirements.txt
mlops/templates/premier-league/charts/plot_metrics.js
expops-0.1.8.dist-info/METADATA
expops-0.1.8.dist-info/WHEEL
expops-0.1.8.dist-info/entry_points.txt
expops-0.1.8.dist-info/top_level.txt
expops-0.1.8.dist-info/RECORD
