Metadata-Version: 2.4
Name: expops
Version: 0.1.8
Summary: MLOps Platform with step-based pipeline execution
License:                     GNU GENERAL PUBLIC LICENSE
Requires-Python: >=3.8
License-File: LICENSE
Requires-Dist: pandas
Requires-Dist: numpy
Requires-Dist: scikit-learn
Requires-Dist: joblib
Requires-Dist: networkx>=2.6
Requires-Dist: PyYAML
Requires-Dist: pydantic>=2
Requires-Dist: dask>=2023.1.0
Requires-Dist: distributed>=2023.1.0
Requires-Dist: lz4==4.0.2
Requires-Dist: redis>=5.0.0
Requires-Dist: google-cloud-firestore>=2.18.0
Requires-Dist: google-cloud-pubsub>=2.20.0
Requires-Dist: google-cloud-storage>=2.18.0
Requires-Dist: fastapi>=0.110
Requires-Dist: uvicorn>=0.25
Provides-Extra: dev
Requires-Dist: pytest; extra == "dev"
Requires-Dist: pytest-cov; extra == "dev"
Provides-Extra: slurm
Requires-Dist: dask-jobqueue>=0.8.0; extra == "slurm"
Dynamic: license-file
